data_overview/__init__.py
data_overview/formatter.py
data_overview/plot.py
data_overview/report.py
data_overview/templates.py
data_overview/data/report.html
data_overview/data/test_data.csv
data_overview/templates/_extra_bar_diagram_row.html
data_overview/templates/_main_bar_diagram_row.html
data_overview/templates/_var_footer.html
data_overview/templates/_var_header.html
data_overview/templates/_var_header_ignore.html
data_overview/templates/column_overview.html
data_overview/templates/content.html
data_overview/templates/data_overview.html
data_overview/templates/extra_bar_diagram.html
data_overview/templates/main_bar_diagram.html
data_overview/templates/var_bool.html
data_overview/templates/var_categorical.html
data_overview/templates/var_constant.html
data_overview/templates/var_date.html
data_overview/templates/var_numeric.html
data_overview/templates/var_unique.html
data_overview/templates/var_unsupported.html
data_overview/templates/wrapper.html
data_overview-0.1.0.dist-info/LICENSE
data_overview-0.1.0.dist-info/METADATA
data_overview-0.1.0.dist-info/WHEEL
data_overview-0.1.0.dist-info/top_level.txt
data_overview-0.1.0.dist-info/RECORD
