Metadata-Version: 2.1
Name: data-overview
Version: 0.1.0
Summary: 数据表概览-数据分析第一步
Home-page: http://blog.duanzhiying.com
Author: kidzying
Author-email: kidzying@163.com
License: UNKNOWN
Platform: UNKNOWN
Classifier: Programming Language :: Python :: 3
Classifier: License :: OSI Approved :: MIT License
Classifier: Operating System :: OS Independent
Requires-Dist: pandas
